Metadata-Version: 1.1
Name: prettyqr
Version: 0.0.2
Summary: Create QR codes merged with images.
Home-page: https://github.com/olorin/prettyqr
Author: Sharif Olorin
Author-email: sio@tesser.org
License: MIT
Keywords: qrcode image
Platform: UNKNOWN
Classifier: Development Status :: 3 - Alpha
Classifier: Intended Audience :: Developers
Classifier: Topic :: Multimedia :: Graphics
Classifier: License :: OSI Approved :: MIT License
Classifier: Programming Language :: Python :: 2
Classifier: Programming Language :: Python :: 2.6
Classifier: Programming Language :: Python :: 2.7
Classifier: Programming Language :: Python :: 3
Classifier: Programming Language :: Python :: 3.3
Classifier: Programming Language :: Python :: 3.4
Classifier: Programming Language :: Python :: 3.5
